utils/__init__.py
utils/utils.py
ZenithCore-0.0.0.dev1.dist-info/METADATA
ZenithCore-0.0.0.dev1.dist-info/WHEEL
ZenithCore-0.0.0.dev1.dist-info/top_level.txt
ZenithCore-0.0.0.dev1.dist-info/RECORD
